ahoorapassword/__init__.py
ahoorapassword-0.1.0.dist-info/licenses/LICENSE
ahoorapassword-0.1.0.dist-info/METADATA
ahoorapassword-0.1.0.dist-info/WHEEL
ahoorapassword-0.1.0.dist-info/top_level.txt
ahoorapassword-0.1.0.dist-info/RECORD
