Metadata-Version: 2.4
Name: ahoorapassword
Version: 0.1.0
Summary: A simple password generator that copies output to clipboard automatically.
Author: AH00RA0
Classifier: Programming Language :: Python :: 3
Classifier: License :: OSI Approved :: MIT License
Classifier: Operating System :: OS Independent
Requires-Python: >=3.6
License-File: LICENSE
Requires-Dist: colorama
Requires-Dist: pyperclip
Dynamic: author
Dynamic: classifier
Dynamic: description
Dynamic: description-content-type
Dynamic: license-file
Dynamic: requires-dist
Dynamic: requires-python
Dynamic: summary
